{
        "label": "AA271001",
        "metadata": [
                {
                        "label": "Titel",
                        "value": "AA271001"
                },
                {
                        "label": "Koker",
                        "value": "Elektrotechniek hoogbouw"
                },
                {
                        "label": "Gebouw",
                        "value": "Elektrotechniek, Wiskunde en Informatica (EWI)"
                }
        ],
        "@id": "https://tu-delft-library.github.io/delta-archief/manifests/AA271001/AA271001",
        "@type": "sc:Collection",
        "@context": "http://iiif.io/api/presentation/2/context.json",
        "manifests": [
                {
                        "@id": "https://tu-delft-library.github.io/delta-archief/manifests/AA271001/500-DB-HB-1-1.json",
                        "label": "HOOGBOUW EERSTE VERDIEPING LINKS",
                        "@type": "sc:Manifest"
                },
                {
                        "@id": "https://tu-delft-library.github.io/delta-archief/manifests/AA271001/500-DB-HB-1-2.json",
                        "label": "HOOGBOUW EERSTE VERDIEPING RECHTER DEEL",
                        "@type": "sc:Manifest"
                },
                {
                        "@id": "https://tu-delft-library.github.io/delta-archief/manifests/AA271001/500-DB-HB-1-3.json",
                        "label": "HOOGBOUW STALEN BINNENPUIEN NO 0113 en 0148 1E VERD.",
                        "@type": "sc:Manifest"
                },
                {
                        "@id": "https://tu-delft-library.github.io/delta-archief/manifests/AA271001/500-DB-HB-1-4.json",
                        "label": "HOOGBOUW CANTINE 1E VERDIEPING DOORSNEDEN \u2013 AANZICHTEN EN DETAILS BORSTWERING",
                        "@type": "sc:Manifest"
                },
                {
                        "@id": "https://tu-delft-library.github.io/delta-archief/manifests/AA271001/500-DB-HB-1-5.json",
                        "label": "HOOGBOUW CANTINE 1E VERDIEPING DETAILS BORSTWERING",
                        "@type": "sc:Manifest"
                },
                {
                        "@id": "https://tu-delft-library.github.io/delta-archief/manifests/AA271001/500-DB-HB-1-6.json",
                        "label": "HOOGBOUW BORST WERING PERS. KANTINE SPOELBAKKEN EN KEUKEN",
                        "@type": "sc:Manifest"
                },
                {
                        "@id": "https://tu-delft-library.github.io/delta-archief/manifests/AA271001/500-DB-HB-1-7.json",
                        "label": "HOOGBOUW BORSTWERIRING PERS. KANTINE SPOELKEUKEN EN KEUKEN",
                        "@type": "sc:Manifest"
                },
                {
                        "@id": "https://tu-delft-library.github.io/delta-archief/manifests/AA271001/500-DB-HB-1-13.json",
                        "label": "HOOGBOUW 1E VERD. LINKER GEDEELTE PLAFONDS",
                        "@type": "sc:Manifest"
                },
                {
                        "@id": "https://tu-delft-library.github.io/delta-archief/manifests/AA271001/500-DB-HB-1-14.json",
                        "label": "HOOGBOUW 1E VERD. RECHTERGEDEELTE PLAFONDS",
                        "@type": "sc:Manifest"
                },
                {
                        "@id": "https://tu-delft-library.github.io/delta-archief/manifests/AA271001/500-DB-HB-1-16.json",
                        "label": "HOOGBOUW KOLOMMEN KANTINE 1E VERDIEPING",
                        "@type": "sc:Manifest"
                },
                {
                        "@id": "https://tu-delft-library.github.io/delta-archief/manifests/AA271001/500-DB-HB-1-17.json",
                        "label": "HOOGBOUW PLAATSTALEN KOZIJNEN V.D. KEUKEN EERSTE VERDIEPING",
                        "@type": "sc:Manifest"
                },
                {
                        "@id": "https://tu-delft-library.github.io/delta-archief/manifests/AA271001/500-DB-HB-1-18.json",
                        "label": "HOOGBOUW PLAFOND KEUKEN EN PERS. KANTINE",
                        "@type": "sc:Manifest"
                },
                {
                        "@id": "https://tu-delft-library.github.io/delta-archief/manifests/AA271001/500-DB-HB-1-21.json",
                        "label": "HOOGBOUW WASEMSCHERM UITGIFTEKEUKEN",
                        "@type": "sc:Manifest"
                },
                {
                        "@id": "https://tu-delft-library.github.io/delta-archief/manifests/AA271001/500-DB-HB-1-22.json",
                        "label": "HOOGDBOUW EERSTE VERD. LINKS DOORVOERINGEN KEUKENVLOER",
                        "@type": "sc:Manifest"
                },
                {
                        "@id": "https://tu-delft-library.github.io/delta-archief/manifests/AA271001/500-DB-HB-1-23.json",
                        "label": "HOOGBOUW DEURVLEUGELS DOORDRAAIENDE DEUREN KEUKEN",
                        "@type": "sc:Manifest"
                },
                {
                        "@id": "https://tu-delft-library.github.io/delta-archief/manifests/AA271001/500-DB-HB-1-24.json",
                        "label": "DOORGEEFLUIKEN TUSSEN UITGIFTE \u2013 en WARMTE KEUKEN",
                        "@type": "sc:Manifest"
                },
                {
                        "@id": "https://tu-delft-library.github.io/delta-archief/manifests/AA271001/500-DB-HB-1-25.json",
                        "label": "HOOGBOUW WASEMKAPPEN WARMTE KEUKEN",
                        "@type": "sc:Manifest"
                },
                {
                        "@id": "https://tu-delft-library.github.io/delta-archief/manifests/AA271001/500-DB-HB-1-26.json",
                        "label": "HOOGBOUW WASEMSCHERM IN KOFFIEKEUKEN",
                        "@type": "sc:Manifest"
                },
                {
                        "@id": "https://tu-delft-library.github.io/delta-archief/manifests/AA271001/500-DB-HB-1-27.json",
                        "label": "HOOGBOUW KEUKEN DEUREN BEKLEED MET MIPOLAM",
                        "@type": "sc:Manifest"
                },
                {
                        "@id": "https://tu-delft-library.github.io/delta-archief/manifests/AA271001/500-DB-HB-1-28.json",
                        "label": "AANSLUITING DETAIL VOUWWAND RAAM UNIT. 1E VERD. KANTINE",
                        "@type": "sc:Manifest"
                },
                {
                        "@id": "https://tu-delft-library.github.io/delta-archief/manifests/AA271001/500-DB-HB-B-54.json",
                        "label": "HOOGBOUW BEGANE GROND GEWIJZIGD PLAFOND HAL",
                        "@type": "sc:Manifest"
                },
                {
                        "@id": "https://tu-delft-library.github.io/delta-archief/manifests/AA271001/500-DB-HB-B-55.json",
                        "label": "HOOGBOUW BEGANE GROND VERLAAGD DEMPO PLAFOND MET LICHTKOVEN",
                        "@type": "sc:Manifest"
                },
                {
                        "@id": "https://tu-delft-library.github.io/delta-archief/manifests/AA271001/500-DB-HB-B-56.json",
                        "label": "HOOGBOUW BEGANE GROND ACHTERINGANG NIEUWE OPSTELLING TOR MAX AANDRIJVING. EXRTA TORMAX AANDRIJVING",
                        "@type": "sc:Manifest"
                },
                {
                        "@id": "https://tu-delft-library.github.io/delta-archief/manifests/AA271001/500-DB-HB-B-57.json",
                        "label": "HOOGBOUW ACHTERINGANG DETAILS NIEUWE OPSTELLING TORMAX DEURAANDRIJVING BEHOORT BIJ BLAD 500-DB-HB-B-56",
                        "@type": "sc:Manifest"
                },
                {
                        "@id": "https://tu-delft-library.github.io/delta-archief/manifests/AA271001/500-DB-HB-B-58.json",
                        "label": "HOOGBOUW RUIT BOVEN PORTIERSLOGE",
                        "@type": "sc:Manifest"
                }
        ]
}