{
        "label": "AA270987",
        "metadata": [
                {
                        "label": "Titel",
                        "value": "AA270987"
                },
                {
                        "label": "Koker",
                        "value": "Sted. Voorst."
                },
                {
                        "label": "Gebouw",
                        "value": "Science Centre Delft"
                }
        ],
        "@id": "https://tu-delft-library.github.io/delta-archief/manifests/AA270987/AA270987",
        "@type": "sc:Collection",
        "@context": "http://iiif.io/api/presentation/2/context.json",
        "manifests": [
                {
                        "@id": "https://tu-delft-library.github.io/delta-archief/manifests/AA270987/1I.json",
                        "label": "KELDER",
                        "@type": "sc:Manifest"
                },
                {
                        "@id": "https://tu-delft-library.github.io/delta-archief/manifests/AA270987/2I(1).json",
                        "label": "BEGANE GROND",
                        "@type": "sc:Manifest"
                },
                {
                        "@id": "https://tu-delft-library.github.io/delta-archief/manifests/AA270987/2I(2).json",
                        "label": "UITBREIDING VAN DE TECHNISCHE HOGESCHOOL DELFT",
                        "@type": "sc:Manifest"
                },
                {
                        "@id": "https://tu-delft-library.github.io/delta-archief/manifests/AA270987/3I.json",
                        "label": "1E VERDIEPING",
                        "@type": "sc:Manifest"
                },
                {
                        "@id": "https://tu-delft-library.github.io/delta-archief/manifests/AA270987/4I.json",
                        "label": "2E VEREDIEPING",
                        "@type": "sc:Manifest"
                },
                {
                        "@id": "https://tu-delft-library.github.io/delta-archief/manifests/AA270987/62.1.json",
                        "label": "TOEGANG KERNREAKTOR MET RINGSLOOT",
                        "@type": "sc:Manifest"
                },
                {
                        "@id": "https://tu-delft-library.github.io/delta-archief/manifests/AA270987/A.json",
                        "label": "GEEN OMSCHRIJVING",
                        "@type": "sc:Manifest"
                },
                {
                        "@id": "https://tu-delft-library.github.io/delta-archief/manifests/AA270987/B3.json",
                        "label": "UITBREIDINGSPLAN",
                        "@type": "sc:Manifest"
                },
                {
                        "@id": "https://tu-delft-library.github.io/delta-archief/manifests/AA270987/D.json",
                        "label": "VOORSTEL AANSLUITING KLUYVERWEG BERLAGEWEG",
                        "@type": "sc:Manifest"
                },
                {
                        "@id": "https://tu-delft-library.github.io/delta-archief/manifests/AA270987/ES-2.json",
                        "label": "GEEN OMSCHRIJVING",
                        "@type": "sc:Manifest"
                },
                {
                        "@id": "https://tu-delft-library.github.io/delta-archief/manifests/AA270987/GEEN TEKENINGNUMMER.json",
                        "label": "BESTRATING RONDOM DIENSTWONINGEN BIJ DE KERNREACTOR AAN DE WATERMANWEG",
                        "@type": "sc:Manifest"
                },
                {
                        "@id": "https://tu-delft-library.github.io/delta-archief/manifests/AA270987/GEEN TEKENINGNUMMER(1).json",
                        "label": "GEEN OMSCHRIJVING",
                        "@type": "sc:Manifest"
                },
                {
                        "@id": "https://tu-delft-library.github.io/delta-archief/manifests/AA270987/GEEN TEKENINGNUMMER(2).json",
                        "label": "UITBREIDING V.D. TECHN. HOGESCHOOL TE DELFT",
                        "@type": "sc:Manifest"
                },
                {
                        "@id": "https://tu-delft-library.github.io/delta-archief/manifests/AA270987/K3-A.json",
                        "label": "TIJDELIJKE AANSLUITING BERLAGEWEG KLUYVERWEG",
                        "@type": "sc:Manifest"
                },
                {
                        "@id": "https://tu-delft-library.github.io/delta-archief/manifests/AA270987/K3.json",
                        "label": "CIRQUIT KENREAKTOR",
                        "@type": "sc:Manifest"
                },
                {
                        "@id": "https://tu-delft-library.github.io/delta-archief/manifests/AA270987/K5.json",
                        "label": "VOORSTEL WIJZEGINGEN AANLUITING BERLAGEWEG \u2013 KLUYVERWEG",
                        "@type": "sc:Manifest"
                },
                {
                        "@id": "https://tu-delft-library.github.io/delta-archief/manifests/AA270987/M1I.json",
                        "label": "RIJWIELSTALLING T.B.V. WINDTUNNELBEB.",
                        "@type": "sc:Manifest"
                },
                {
                        "@id": "https://tu-delft-library.github.io/delta-archief/manifests/AA270987/M2.json",
                        "label": "SITUATIE METAALKUNDE AERO \u2013 EN HYDRODYNAMIKA, KETELHUIS, WINDTUNNEL",
                        "@type": "sc:Manifest"
                },
                {
                        "@id": "https://tu-delft-library.github.io/delta-archief/manifests/AA270987/M3.json",
                        "label": "RIJWIELSTALLING T.B.V. KETELHUIS",
                        "@type": "sc:Manifest"
                },
                {
                        "@id": "https://tu-delft-library.github.io/delta-archief/manifests/AA270987/M4-1.json",
                        "label": "BESTAANDE TOESTAND TNO METAALINSTITUUT",
                        "@type": "sc:Manifest"
                },
                {
                        "@id": "https://tu-delft-library.github.io/delta-archief/manifests/AA270987/M4-2.json",
                        "label": "PARKEERGELEGENHEID T.N.O. METAALINSTITUUT \u2013 SCHAAL 1100",
                        "@type": "sc:Manifest"
                },
                {
                        "@id": "https://tu-delft-library.github.io/delta-archief/manifests/AA270987/S1.json",
                        "label": "PLAN STUDENTENHUISVESTING",
                        "@type": "sc:Manifest"
                },
                {
                        "@id": "https://tu-delft-library.github.io/delta-archief/manifests/AA270987/S2.json",
                        "label": "PLAN STUDENTENHUISVESTING",
                        "@type": "sc:Manifest"
                },
                {
                        "@id": "https://tu-delft-library.github.io/delta-archief/manifests/AA270987/S4.json",
                        "label": "STUDENTENHUISVESTING TEN ZUIDEN VAN HET GEBOUW VAN BOUWKUNDE SCHAAL 11000",
                        "@type": "sc:Manifest"
                },
                {
                        "@id": "https://tu-delft-library.github.io/delta-archief/manifests/AA270987/T1.json",
                        "label": "SITUATTIE SCHEIKUNDE",
                        "@type": "sc:Manifest"
                },
                {
                        "@id": "https://tu-delft-library.github.io/delta-archief/manifests/AA270987/T1a.json",
                        "label": "VOORSTEL TE MAKEN PARKEERGELEGENHEID. T.B.V. GEBOUW VOOR SCHEIKUNDE AAN DE PRINS BERNHARDLAAN",
                        "@type": "sc:Manifest"
                },
                {
                        "@id": "https://tu-delft-library.github.io/delta-archief/manifests/AA270987/T2.json",
                        "label": "SITUATIE OUDE EN NIEUWE TOESTAND FIETSENSTALLING EN PARKEERGELEGENHEID SCHEIKUNDE",
                        "@type": "sc:Manifest"
                },
                {
                        "@id": "https://tu-delft-library.github.io/delta-archief/manifests/AA270987/T3.json",
                        "label": "SITUATIE TERREIN NAAST SCHEIKUNDE AAN DE JULIANALAAN",
                        "@type": "sc:Manifest"
                },
                {
                        "@id": "https://tu-delft-library.github.io/delta-archief/manifests/AA270987/WL-1.json",
                        "label": "INDELING TERREIN TEN NOORDEN VAN DE KARITAAT MOLENSLOOT T.B.V. WATERLOOPK. LAB EN PROEFBASSIN",
                        "@type": "sc:Manifest"
                }
        ]
}